cellar/__init__.py
cellar/fs.py
cellar/menu.py
cellar/password.py
cellar/photos.py
cellar/settings.py
cellar/web.py
cellarpy-1.3.dist-info/DESCRIPTION.rst
cellarpy-1.3.dist-info/METADATA
cellarpy-1.3.dist-info/RECORD
cellarpy-1.3.dist-info/WHEEL
cellarpy-1.3.dist-info/metadata.json
cellarpy-1.3.dist-info/top_level.txt
