Metadata-Version: 2.0
Name: cellarpy
Version: 1.3
Summary: cellarpy empower python web-applications based on bottlepy
Home-page: https://github.com/JonathanHuot/cellarpy
Author: Jonathan Huot
Author-email: jonathan.huot@gmail.com
License: MIT
Keywords: bottle web wsgi
Platform: UNKNOWN
Classifier: Development Status :: 5 - Production/Stable
Classifier: Intended Audience :: Developers
Classifier: License :: OSI Approved :: MIT License
Classifier: Topic :: Software Development :: Libraries :: Application Frameworks
Classifier: Framework :: Bottle
Classifier: Programming Language :: Python :: 2.7
Classifier: Programming Language :: Python :: 3
Classifier: Programming Language :: Python :: 3.3
Classifier: Programming Language :: Python :: 3.4
Classifier: Programming Language :: Python :: 3.6
